QConnectBase/QConnectBase.pdf
QConnectBase/__init__.py
QConnectBase/connection_base.py
QConnectBase/connection_manager.py
QConnectBase/constants.py
QConnectBase/qlogger.py
QConnectBase/utils.py
QConnectBase/version.py
QConnectBase/message/__init__.py
QConnectBase/message/rabbitmq_client.py
QConnectBase/serialclient/__init__.py
QConnectBase/serialclient/serial_base.py
QConnectBase/tcp/__init__.py
QConnectBase/tcp/tcp_base.py
QConnectBase/tcp/raw/__init__.py
QConnectBase/tcp/raw/raw_tcp.py
QConnectBase/tcp/ssh/__init__.py
QConnectBase/tcp/ssh/ssh_client.py
robotframework_qconnect_base-1.3.0.dist-info/licenses/LICENSE
robotframework_qconnect_base-1.3.0.dist-info/METADATA
robotframework_qconnect_base-1.3.0.dist-info/WHEEL
robotframework_qconnect_base-1.3.0.dist-info/top_level.txt
robotframework_qconnect_base-1.3.0.dist-info/RECORD
