Metadata-Version: 2.4
Name: robotframework-qconnect-base
Version: 1.3.0
Summary: Robot Framework test library for TCP, SSH, serial connection
Home-page: https://github.com/test-fullautomation/robotframework-qconnect-base
Author: Nguyen Huynh Tri Cuong
Author-email: cuong.nguyenhuynhtri@vn.bosch.com
Classifier: Programming Language :: Python :: 3
Classifier: License :: OSI Approved :: Apache Software License
Classifier: Operating System :: OS Independent
Classifier: Development Status :: 4 - Beta
Classifier: Intended Audience :: Developers
Classifier: Topic :: Software Development
Requires-Python: >=3.0
License-File: LICENSE
Requires-Dist: robotframework
Requires-Dist: paramiko
Requires-Dist: pyserial
Dynamic: author
Dynamic: author-email
Dynamic: classifier
Dynamic: description
Dynamic: description-content-type
Dynamic: home-page
Dynamic: license-file
Dynamic: requires-dist
Dynamic: requires-python
Dynamic: summary
